{"id":"17dae1c4-efe6-4a5d-a549-67bf1534bf21","name":"Moving Matrix Position Center Stage Upwards","deviceParams":[{"group":"76b3a740-0086-4854-b56d-ad4e50ccf540","device":null,"params":[{"ledAll":true,"led":0,"$color":null,"red":null,"green":null,"blue":null,"white":null,"pan":128,"tilt":64,"strobe":null,"mode":null,"dimmer":null}],"animation":null,"transition":null},{"group":"3abc39c4-4fbd-4fcf-badd-c35a6fca09a1","device":null,"params":[{"ledAll":true,"led":0,"$color":null,"red":null,"green":null,"blue":null,"white":null,"pan":40,"tilt":64,"strobe":null,"mode":null,"dimmer":null}],"animation":null,"transition":null}]}